looker_aggregate_builder/__init__.py
looker_aggregate_builder/cli/__init__.py
looker_aggregate_builder/cli/lab_cli.py
dna_looker_aggregate_builder-0.0.0.dist-info/METADATA
dna_looker_aggregate_builder-0.0.0.dist-info/WHEEL
dna_looker_aggregate_builder-0.0.0.dist-info/entry_points.txt
dna_looker_aggregate_builder-0.0.0.dist-info/top_level.txt
dna_looker_aggregate_builder-0.0.0.dist-info/RECORD
