Metadata-Version: 2.1
Name: dna-looker-aggregate-builder
Version: 0.0.0
Summary: XXXXXX
Author: XXXXX
Author-email: XXXXXX@XXXXX.com
License: UNKNOWN
Platform: UNKNOWN
Classifier: Programming Language :: Python :: 3
Classifier: Operating System :: OS Independent
Requires-Python: >=3.7
Requires-Dist: click (>=8.0.3)
